{"brand":"BLVD","date_range":"2024-01-01 00:00:00 to 2026-02-28 00:00:00","period_label":"All Time","summary":{"total_units":1148,"total_revenue":41254.5703125,"total_cost":17794.0,"total_discounts":10405.4296875,"total_profit":23460.5703125,"overall_margin":56.900001525878906,"fp_margin":65.5999984741211,"disc_margin":55.0,"pct_full_price":17.5,"avg_discount_rate":20.100000381469727,"fp_revenue":7200.0,"disc_revenue":34054.5703125,"unique_customers":613,"brand":"BLVD","date_range":"2024-01-01 00:00:00 to 2026-02-28 00:00:00","months_count":3,"avg_monthly_cost":5931.33,"cost_per_unit":15.5,"primary_category":"FLOWER","primary_cat_margin":54.20000076293945,"category_rank":47,"category_total":64,"margin_vs_category":2.700000047683716,"velocity_rank":48},"category_breakdown":[{"category_clean":"FLOWER","units":1148,"revenue":41254.5703125,"cost":17794.0,"profit":23460.5703125,"discounts":10405.4296875,"margin":56.900001525878906,"category_avg_margin":54.20000076293945,"vs_category":2.7,"rank":47.0,"total_brands":64.0}],"trend":[{"period":"2025-12","revenue":11077.900390625,"cost":4774.0,"margin":56.9,"units":308,"transactions":218,"profit":6303.89990234375,"revenue_change_pct":null,"units_change_pct":null,"margin_change_pts":null},{"period":"2026-01","revenue":14960.490234375,"cost":6417.0,"margin":57.1,"units":414,"transactions":283,"profit":8543.490234375,"revenue_change_pct":35.0,"units_change_pct":34.4,"margin_change_pts":0.2},{"period":"2026-02","revenue":15216.1796875,"cost":6603.0,"margin":56.6,"units":426,"transactions":298,"profit":8613.1796875,"revenue_change_pct":1.7,"units_change_pct":2.9,"margin_change_pts":-0.5}],"share_of_category":[{"category":"FLOWER","brand_revenue":41254.5703125,"category_revenue":32066370.0,"revenue_share_pct":0.10000000149011612,"brand_units":1148,"category_units":1397388,"units_share_pct":0.1}],"share_of_category_trend":{"FLOWER":[{"period":"2024-01","brand_revenue":0.0,"category_revenue":1420943.125,"share_pct":0.0},{"period":"2024-02","brand_revenue":0.0,"category_revenue":1414098.25,"share_pct":0.0},{"period":"2024-03","brand_revenue":0.0,"category_revenue":1477522.25,"share_pct":0.0},{"period":"2024-04","brand_revenue":0.0,"category_revenue":1416759.875,"share_pct":0.0},{"period":"2024-05","brand_revenue":0.0,"category_revenue":1414991.75,"share_pct":0.0},{"period":"2024-06","brand_revenue":0.0,"category_revenue":1361307.875,"share_pct":0.0},{"period":"2024-07","brand_revenue":0.0,"category_revenue":1383082.375,"share_pct":0.0},{"period":"2024-08","brand_revenue":0.0,"category_revenue":1381527.75,"share_pct":0.0},{"period":"2024-09","brand_revenue":0.0,"category_revenue":1326576.625,"share_pct":0.0},{"period":"2024-10","brand_revenue":0.0,"category_revenue":1434310.0,"share_pct":0.0},{"period":"2024-11","brand_revenue":0.0,"category_revenue":1381942.125,"share_pct":0.0},{"period":"2024-12","brand_revenue":0.0,"category_revenue":1290627.125,"share_pct":0.0},{"period":"2025-01","brand_revenue":0.0,"category_revenue":1193975.25,"share_pct":0.0},{"period":"2025-02","brand_revenue":0.0,"category_revenue":1126488.0,"share_pct":0.0},{"period":"2025-03","brand_revenue":0.0,"category_revenue":1164551.875,"share_pct":0.0},{"period":"2025-04","brand_revenue":0.0,"category_revenue":1247558.125,"share_pct":0.0},{"period":"2025-05","brand_revenue":0.0,"category_revenue":1154938.0,"share_pct":0.0},{"period":"2025-06","brand_revenue":0.0,"category_revenue":1109479.25,"share_pct":0.0},{"period":"2025-07","brand_revenue":0.0,"category_revenue":1113105.25,"share_pct":0.0},{"period":"2025-08","brand_revenue":0.0,"category_revenue":1093249.125,"share_pct":0.0},{"period":"2025-09","brand_revenue":0.0,"category_revenue":1041400.625,"share_pct":0.0},{"period":"2025-10","brand_revenue":0.0,"category_revenue":1065482.0,"share_pct":0.0},{"period":"2025-11","brand_revenue":0.0,"category_revenue":1080075.625,"share_pct":0.0},{"period":"2025-12","brand_revenue":11077.900390625,"category_revenue":1006083.8125,"share_pct":1.100000023841858},{"period":"2026-01","brand_revenue":14960.490234375,"category_revenue":1002104.75,"share_pct":1.5},{"period":"2026-02","brand_revenue":15216.1796875,"category_revenue":964188.6875,"share_pct":1.600000023841858}]},"discount_depth":[{"tier":"0% (Full Price)","transactions":151,"pct_of_transactions":17.1,"revenue":7200.0,"avg_discount":0.0},{"tier":"1-10%","transactions":30,"pct_of_transactions":3.4,"revenue":1215.0,"avg_discount":10.0},{"tier":"11-20%","transactions":343,"pct_of_transactions":38.9,"revenue":19257.2890625,"avg_discount":17.0},{"tier":"21-30%","transactions":14,"pct_of_transactions":1.6,"revenue":755.030029296875,"avg_discount":23.9},{"tier":"31%+","transactions":343,"pct_of_transactions":38.9,"revenue":12827.25,"avg_discount":32.3}],"velocity":{"units_per_day":13.05,"revenue_per_day":468.79998779296875,"avg_units_per_txn":1.44,"days_of_data":88,"total_units":1148,"total_transactions":799},"velocity_by_category":[{"category":"FLOWER","brand_units_per_day":1.45,"category_avg_units_per_day":27.64,"velocity_index":5.3,"brand_rev_per_unit":35.94,"category_rev_per_unit":22.95,"brands_in_category":64}],"deals":[{"deal_name":"Lit4Less - 1/4 for $75","times_used":251,"units":451.6666666666667,"revenue":16912.468335469563,"discounts":3412.531666914622,"cost":7000.833333333333,"profit":9911.635001659393,"pre_discount_revenue":20325.0,"margin":58.6,"avg_discount":16.8},{"deal_name":"Industry 30% Off","times_used":203,"units":248.5,"revenue":7773.9699993133545,"discounts":3408.5300006866455,"cost":3851.75,"profit":3922.2200005054474,"pre_discount_revenue":11182.5,"margin":50.5,"avg_discount":30.5},{"deal_name":"Senior / Veterans - 20% Off","times_used":21,"units":27.0,"revenue":967.5,"discounts":247.5,"cost":418.5,"profit":549.0,"pre_discount_revenue":1215.0,"margin":56.7,"avg_discount":20.4},{"deal_name":"Senior - 10% Off","times_used":20,"units":19.0,"revenue":752.310001373291,"discounts":102.6899995803833,"cost":294.5,"profit":457.8099994659424,"pre_discount_revenue":855.0,"margin":60.9,"avg_discount":12.0},{"deal_name":"Jackpot - Locals 30% Off","times_used":16,"units":28.0,"revenue":882.0,"discounts":378.0,"cost":434.0,"profit":448.0,"pre_discount_revenue":1260.0,"margin":50.8,"avg_discount":30.0},{"deal_name":"Employee - 40% OFF","times_used":10,"units":12.0,"revenue":324.0,"discounts":216.0,"cost":186.0,"profit":138.0,"pre_discount_revenue":540.0,"margin":42.6,"avg_discount":40.0},{"deal_name":"35% Off Special","times_used":9,"units":9.0,"revenue":263.25,"discounts":141.75,"cost":139.5,"profit":123.75,"pre_discount_revenue":405.0,"margin":47.0,"avg_discount":35.0},{"deal_name":"40% Off Special","times_used":9,"units":12.0,"revenue":324.0,"discounts":216.0,"cost":186.0,"profit":138.0,"pre_discount_revenue":540.0,"margin":42.6,"avg_discount":40.0},{"deal_name":"Employee 30% - NOT FRIDAYS","times_used":9,"units":10.5,"revenue":278.25,"discounts":194.25,"cost":162.75,"profit":115.5,"pre_discount_revenue":472.5,"margin":41.5,"avg_discount":41.1},{"deal_name":"Store Credit - $25","times_used":9,"units":8.166666666666666,"revenue":243.97333463033038,"discounts":123.52666727701822,"cost":126.58333333333333,"profit":117.39000225067139,"pre_discount_revenue":367.5,"margin":48.1,"avg_discount":33.6},{"deal_name":"Store Credit - $15","times_used":8,"units":11.666666666666666,"revenue":342.4083302815755,"discounts":182.5916659037272,"cost":180.83333333333334,"profit":161.57500076293945,"pre_discount_revenue":525.0,"margin":47.2,"avg_discount":34.8},{"deal_name":"Veterans - 10% Off","times_used":8,"units":8.0,"revenue":324.0,"discounts":36.0,"cost":124.0,"profit":200.0,"pre_discount_revenue":360.0,"margin":61.7,"avg_discount":10.0},{"deal_name":"Store Credit - $50","times_used":5,"units":4.0,"revenue":107.8849983215332,"discounts":72.11500024795532,"cost":62.0,"profit":45.88499999046326,"pre_discount_revenue":180.0,"margin":42.5,"avg_discount":40.1},{"deal_name":"Store Credit - $75","times_used":2,"units":1.5,"revenue":46.685001373291016,"discounts":20.8149995803833,"cost":23.25,"profit":23.434999465942383,"pre_discount_revenue":67.5,"margin":50.2,"avg_discount":30.8},{"deal_name":"LVAC - 25% Off","times_used":1,"units":1.0,"revenue":33.75,"discounts":11.25,"cost":15.5,"profit":18.25,"pre_discount_revenue":45.0,"margin":54.1,"avg_discount":25.0},{"deal_name":"Medical - 10%","times_used":1,"units":1.0,"revenue":40.5,"discounts":4.5,"cost":15.5,"profit":25.0,"pre_discount_revenue":45.0,"margin":61.7,"avg_discount":10.0}],"top_products":[{"product":"702 HEADBAND EIGHTH - BLVD","units":415,"revenue":15112.1396484375,"cost":6432.5,"profit":8679.6396484375,"transactions":327,"margin":57.400001525878906},{"product":"CAP JUNKIE EIGHTH - BLVD","units":292,"revenue":10360.669921875,"cost":4526.0,"profit":5834.669921875,"transactions":227,"margin":56.29999923706055},{"product":"STARFRUITZ EIGHTH - BLVD","units":177,"revenue":6362.72021484375,"cost":2743.5,"profit":3619.219970703125,"transactions":131,"margin":56.900001525878906},{"product":"NAKED CITY GUSHERS EIGHTH - BLVD","units":137,"revenue":4910.2099609375,"cost":2123.5,"profit":2786.7099609375,"transactions":101,"margin":56.79999923706055},{"product":"GREYHOUND EIGHTH - BLVD","units":127,"revenue":4508.830078125,"cost":1968.5,"profit":2540.330078125,"transactions":95,"margin":56.29999923706055}],"products_by_store":{"Thrive Cactus":[{"product":"702 HEADBAND EIGHTH - BLVD","units":86,"revenue":3084.75,"cost":1333.0,"profit":1751.75,"transactions":72,"margin":56.79999923706055},{"product":"CAP JUNKIE EIGHTH - BLVD","units":37,"revenue":1337.25,"cost":573.5,"profit":763.75,"transactions":37,"margin":57.099998474121094},{"product":"NAKED CITY GUSHERS EIGHTH - BLVD","units":32,"revenue":1210.5,"cost":496.0,"profit":714.5,"transactions":29,"margin":59.0},{"product":"STARFRUITZ EIGHTH - BLVD","units":32,"revenue":1173.5,"cost":496.0,"profit":677.5,"transactions":25,"margin":57.70000076293945},{"product":"GREYHOUND EIGHTH - BLVD","units":31,"revenue":1091.5,"cost":480.5,"profit":611.0,"transactions":20,"margin":56.0}],"Thrive Cheyenne":[{"product":"702 HEADBAND EIGHTH - BLVD","units":95,"revenue":3266.18994140625,"cost":1472.5,"profit":1793.68994140625,"transactions":82,"margin":54.900001525878906},{"product":"CAP JUNKIE EIGHTH - BLVD","units":79,"revenue":2638.090087890625,"cost":1224.5,"profit":1413.5899658203125,"transactions":66,"margin":53.599998474121094},{"product":"STARFRUITZ EIGHTH - BLVD","units":54,"revenue":1803.719970703125,"cost":837.0,"profit":966.719970703125,"transactions":45,"margin":53.599998474121094},{"product":"NAKED CITY GUSHERS EIGHTH - BLVD","units":31,"revenue":1055.25,"cost":480.5,"profit":574.75,"transactions":19,"margin":54.5},{"product":"GREYHOUND EIGHTH - BLVD","units":32,"revenue":1026.5,"cost":496.0,"profit":530.5,"transactions":28,"margin":51.70000076293945}],"Thrive Jackpot":[{"product":"702 HEADBAND EIGHTH - BLVD","units":119,"revenue":4593.6201171875,"cost":1844.5,"profit":2749.1201171875,"transactions":78,"margin":59.79999923706055},{"product":"CAP JUNKIE EIGHTH - BLVD","units":96,"revenue":3671.75,"cost":1488.0,"profit":2183.75,"transactions":59,"margin":59.5},{"product":"STARFRUITZ EIGHTH - BLVD","units":71,"revenue":2662.5,"cost":1100.5,"profit":1562.0,"transactions":45,"margin":58.70000076293945},{"product":"GREYHOUND EIGHTH - BLVD","units":32,"revenue":1189.0,"cost":496.0,"profit":693.0,"transactions":23,"margin":58.29999923706055},{"product":"NAKED CITY GUSHERS EIGHTH - BLVD","units":25,"revenue":894.5700073242188,"cost":387.5,"profit":507.07000732421875,"transactions":16,"margin":56.70000076293945}],"Thrive Reno":[{"product":"702 HEADBAND EIGHTH - BLVD","units":74,"revenue":2822.179931640625,"cost":1147.0,"profit":1675.1800537109375,"transactions":58,"margin":59.400001525878906},{"product":"CAP JUNKIE EIGHTH - BLVD","units":50,"revenue":1824.8299560546875,"cost":775.0,"profit":1049.8299560546875,"transactions":39,"margin":57.5},{"product":"GREYHOUND EIGHTH - BLVD","units":32,"revenue":1201.8299560546875,"cost":496.0,"profit":705.8300170898438,"transactions":24,"margin":58.70000076293945},{"product":"NAKED CITY GUSHERS EIGHTH - BLVD","units":32,"revenue":1180.5,"cost":496.0,"profit":684.5,"transactions":20,"margin":58.0},{"product":"STARFRUITZ EIGHTH - BLVD","units":12,"revenue":451.5,"cost":186.0,"profit":265.5,"transactions":9,"margin":58.79999923706055}],"Thrive Sahara":[{"product":"702 HEADBAND EIGHTH - BLVD","units":41,"revenue":1345.4000244140625,"cost":635.5,"profit":709.9000244140625,"transactions":37,"margin":52.79999923706055},{"product":"CAP JUNKIE EIGHTH - BLVD","units":30,"revenue":888.75,"cost":465.0,"profit":423.75,"transactions":26,"margin":47.70000076293945},{"product":"NAKED CITY GUSHERS EIGHTH - BLVD","units":17,"revenue":569.3900146484375,"cost":263.5,"profit":305.8900146484375,"transactions":17,"margin":53.70000076293945},{"product":"STARFRUITZ EIGHTH - BLVD","units":8,"revenue":271.5,"cost":124.0,"profit":147.5,"transactions":7,"margin":54.29999923706055}]},"store_summary":[{"store_clean":"Thrive Jackpot","units":343,"revenue":13011.4404296875,"cost":5316.5,"profit":7694.93994140625,"discounts":2423.56005859375,"margin":59.099998474121094,"discount_rate":15.699999809265137},{"store_clean":"Thrive Cheyenne","units":291,"revenue":9789.75,"cost":4510.5,"profit":5279.25,"discounts":3305.25,"margin":53.900001525878906,"discount_rate":25.200000762939453},{"store_clean":"Thrive Cactus","units":218,"revenue":7897.5,"cost":3379.0,"profit":4518.5,"discounts":1912.5,"margin":57.20000076293945,"discount_rate":19.5},{"store_clean":"Thrive Reno","units":200,"revenue":7480.83984375,"cost":3100.0,"profit":4380.83984375,"discounts":1519.1600341796875,"margin":58.599998474121094,"discount_rate":16.899999618530273},{"store_clean":"Thrive Sahara","units":96,"revenue":3075.0400390625,"cost":1488.0,"profit":1587.0400390625,"discounts":1244.9599609375,"margin":51.599998474121094,"discount_rate":28.799999237060547}],"recommendations":[{"severity":"red","title":"HIGH PROMOTION DEPENDENCY","detail":"Only 18% sells at full price. Heavy discounting required.","action":"Test reducing deal frequency \u2014 track velocity without promos."},{"severity":"info","title":"VOLUME LEVERAGE","detail":"$41,255 revenue provides negotiating leverage.","action":"Use volume as leverage in next vendor meeting."}],"comparison":null}